{
    "AS_Button_ec937fea35864e6b993cbd6e1215d35f": {
        "id": "AS_Button_ec937fea35864e6b993cbd6e1215d35f",
        "type": "ACTION_SEQUENCE",
        "params": [{
            "datatype": "collection",
            "name": "eventobject"
        }],
        "contextObj": {
            "name": "frmBioToggleUniken",
            "type": "forms",
            "platform": null,
            "KUID": "c653c80ad50b4778ae768810d301a157"
        },
        "language": "js",
        "actions": [{
            "id": "ADD_SNIPPET_ide_onClick_ab535ad59d684a3f80db831a5ae666b7",
            "type": "ADD_SNIPPET",
            "codeSnippet": "this.btnSkipOnClick();",
            "callbackType": null
        }]
    }
}