{
    "@class": "com.kony.gen.viz.model.component.KVizButton",
    "DNDConfig": null,
    "_bottom_": {
        "type": "string",
        "value": "25%"
    },
    "_height_": {
        "type": "string",
        "value": "7%"
    },
    "_left_": {
        "type": "string",
        "value": "7%"
    },
    "_margin_": [
        6,
        6,
        6,
        6
    ],
    "_padding_": [
        0,
        0,
        0,
        0
    ],
    "_right_": {
        "type": "string",
        "value": "7%"
    },
    "_skin_": "sc61e719c72447bf9f14db24bea23eb3",
    "_text_": "Approve",
    "accessibilityconfig": {
        "a11yHint": "Tap Set as Default to make this the default choice",
        "a11yLabel": "Set as Default"
    },
    "canUpdateUI": true,
    "centerx": {
        "type": "string",
        "value": "49.99%"
    },
    "containerweight": 100,
    "contentalignment": 5,
    "disabledSkins": {},
    "displaytext": true,
    "focusskin": "sd85a0f475ff4b3b9f0a5e4b82f68213",
    "id": "btnApprove",
    "ide_onClick": "AS_Button_fedb04657eae468f827bea9a5106f09d",
    "info": null,
    "iphone": {
        "psp": {
            "showProgressIndicator": false
        }
    },
    "isvisible": true,
    "kuid": "c8e0c83a181b4f8a874fd05c8dd969b0",
    "name": "kony.ui.Button",
    "parent": "flxMainContainer",
    "pf": "frmBiometricApprovalUniken",
    "wType": "Button",
    "zindex": 1
}