{
  "android": {
    "border_color": "6c79cbff",
    "border_type": 0,
    "bottom_left_border_radius": 8,
    "bottom_right_border_radius": 8,
    "font_name": "SourceSansPro-Regular",
    "font_size": 109,
    "isForked": true,
    "top_left_border_radius": 8,
    "top_right_border_radius": 8
  },
  "androidwearos": {
    "border_color": "0a0a0aff",
    "border_type": 0,
    "font_size": 150,
    "isForked": true
  },
  "background_color": "0a0a0aff",
  "bg_type": "one",
  "border_color": "6C79CBff",
  "border_radius": 8,
  "border_style": "custom",
  "border_type": 0,
  "border_width": 1,
  "desktopweb": {
    "bottom_left_border_color": "6C79CBff",
    "bottom_left_border_radius": 8,
    "bottom_left_border_style": "rc",
    "bottom_left_border_width": 1,
    "bottom_right_border_color": "6C79CBff",
    "bottom_right_border_radius": 8,
    "bottom_right_border_style": "rc",
    "bottom_right_border_width": 1,
    "font_size": 234,
    "isForked": true,
    "top_left_border_color": "6C79CBff",
    "top_left_border_radius": 8,
    "top_left_border_style": "rc",
    "top_left_border_width": 1,
    "top_right_border_color": "6C79CBff",
    "top_right_border_radius": 8,
    "top_right_border_style": "rc",
    "top_right_border_width": 1
  },
  "fontSizeInPx": true,
  "font_color": "6C79CBff",
  "font_name": "SourceSansPro-Regular",
  "font_size": 109,
  "font_style": "normal",
  "font_weight": "400",
  "ipad": {
    "border_color": "0a0a0aff",
    "border_type": 0,
    "font_name": "SourceSansPro-Regular",
    "font_size": 150,
    "isForked": true
  },
  "iphone": {
    "border_color": "6c79cbff",
    "border_type": 0,
    "font_name": "SourceSansPro-Regular",
    "font_size": 150,
    "isForked": true
  },
  "isDefaultSkin": false,
  "kuid": "s61262a2e7e14deaa0157536ef889c3b",
  "tabrcandroid": {
    "border_color": "0a0a0aff",
    "border_type": 0,
    "font_name": "SourceSansPro-Regular",
    "font_size": 234,
    "isForked": true
  },
  "wType": "Button",
  "watchos": {
    "font_size": 150,
    "isForked": true
  }
}