{
  "android": {
    "font_name": "SourceSansPro-SemiBold",
    "font_size": 109,
    "isForked": true
  },
  "background_color": "6C79CBff",
  "bg_type": "one",
  "border_color": "0a0a0aff",
  "border_style": "plain",
  "border_type": 0,
  "border_width": 0,
  "fontSizeInPx": true,
  "font_color": "0a0a0aff",
  "font_name": "SourceSansPro-Regular",
  "font_size": 125,
  "font_style": "normal",
  "font_weight": "400",
  "iphone": {
    "font_name": "SourceSansPro-SemiBold",
    "font_size": 92,
    "isForked": true
  },
  "isDefaultSkin": false,
  "kuid": "sa8ffb4a89744618872c041e41258d51",
  "wType": "Button"
}