{
  "android": {
    "font_name": "SourceSansPro-Regular"
  },
  "androidwearos": {
    "font_name": "SourceSansPro-Regular"
  },
  "background_color": "00000000",
  "bg_type": "one",
  "border_color": "424242ff",
  "border_style": "plain",
  "border_type": 0,
  "border_width": 0,
  "desktopweb": {
    "font_name": "SourceSansPro-Regular"
  },
  "font_color": "333333ff",
  "font_name": "SourceSansPro-Regular",
  "font_size": 200,
  "font_style": "normal",
  "font_weight": "400",
  "ipad": {
    "font_name": "SourceSansPro-Regular"
  },
  "iphone": {
    "font_name": "SourceSansPro-Regular"
  },
  "isDefaultSkin": false,
  "kuid": "s53de41115b64229a3d0b355c18eeb66",
  "tabrcandroid": {
    "font_name": "SourceSansPro-Regular"
  },
  "wType": "Label",
  "watchos": {
    "font_name": "SourceSansPro-Regular"
  }
}