{
  "android": {
    "font_name": "SourceSansPro-Regular",
    "font_size": 109,
    "isForked": false
  },
  "androidwearos": {
    "font_name": "SourceSansPro-Regular"
  },
  "background_color": "0a0a0aff",
  "bg_type": "one",
  "border_color": "d62c3aff",
  "border_radius": 8,
  "border_style": "custom",
  "border_type": 0,
  "border_width": 2,
  "desktopweb": {
    "font_name": "SourceSansPro-Regular",
    "font_size": 109,
    "isForked": false
  },
  "fontSizeInPx": false,
  "font_color": "eeeeeeff",
  "font_name": "SourceSansPro-Regular",
  "font_size": 109,
  "font_style": "normal",
  "font_weight": "normal",
  "ipad": {
    "font_name": "SourceSansPro-Regular",
    "font_size": 109,
    "isForked": false
  },
  "iphone": {
    "font_name": "SourceSansPro-Regular",
    "font_size": 109,
    "isForked": false
  },
  "isDefaultSkin": false,
  "kuid": "s843139ff99e468596cfe6a34c8dedf7",
  "tabrcandroid": {
    "font_name": "SourceSansPro-Regular",
    "font_size": 109,
    "isForked": false
  },
  "wType": "TextField",
  "watchos": {
    "font_name": "SourceSansPro-Regular",
    "font_size": 109,
    "isForked": false
  }
}