{
    "@class": "com.kony.gen.viz.model.component.KVizUserWidget",
    "DNDConfig": null,
    "_children_": [],
    "_height_": {
        "type": "ref",
        "value": "preferred"
    },
    "_left_": {
        "type": "string",
        "value": "65%"
    },
    "_margin_": [
        0,
        0,
        0,
        0
    ],
    "_orientation_": 1,
    "_padding_": [
        0,
        0,
        0,
        0
    ],
    "_percent_": true,
    "_render_": true,
    "_skin_": "s24c92fc23b14f5484b693ee9b8a9b35",
    "_top_": {
        "type": "string",
        "value": "350dp"
    },
    "_width_": {
        "type": "string",
        "value": "28.48%"
    },
    "areflexpropsreferenced": false,
    "autogrowmode": 1,
    "canUpdateUI": true,
    "clipbounds": false,
    "containerweight": 0,
    "dataDiffs": {
        "accountTypes": {
            "__events__": {},
            "__info__": {
                "isRoot": true,
                "kuid": "f4c7015efc5d4827bd5dd8a218249bfe",
                "srcKUID": "b62c12eb1c8d4c288d0cc6b63f1eb6bb",
                "wType": "FlexContainer"
            },
            "autogrowMode": 1,
            "height": {
                "Default": {
                    "type": "ref",
                    "value": "preferred"
                }
            },
            "isVisible": false,
            "left": {
                "Default": {
                    "type": "string",
                    "value": "65%"
                }
            },
            "responsiveData": {},
            "top": {
                "Default": {
                    "type": "string",
                    "value": "350dp"
                }
            },
            "vizProps": {
                "hide": true
            },
            "width": {
                "Default": {
                    "type": "string",
                    "value": "28.48%"
                }
            },
            "zIndex": {
                "Default": 10
            }
        },
        "flxAccountTypesSegment": {
            "__events__": {},
            "__info__": {
                "kuid": "d9388f6a0d594d5582bd174b9b5c5262",
                "srcKUID": "012bfaa77f29418e90e76556de8e6db8",
                "wType": "FlexContainer"
            },
            "autogrowMode": 1,
            "height": {
                "Default": {
                    "type": "ref",
                    "value": "preferred"
                }
            }
        },
        "imgToolTip": {
            "__events__": {},
            "__info__": {
                "kuid": "b831aa822a4b4c30918e766465c288ca",
                "srcKUID": "38b535966b4c476e9b87c15b828b2245",
                "wType": "Image"
            },
            "left": {
                "Default": {
                    "type": "string",
                    "value": "86.50%"
                }
            },
            "src": "tool_tip.png"
        },
        "segAccountTypes": {
            "__events__": {},
            "__info__": {
                "kuid": "c44274e31baa4f89b0062f6a976c680e",
                "srcKUID": "d42b5ca698e0494ca8a5e305a01a9418",
                "wType": "Segment"
            },
            "autogrowMode": 1,
            "data": {
                "desktop": [
                    {
                        "lblSeparator": {
                            "@class": "com.viz.ide.model.segment.SimpleTextSegmentData",
                            "text": "Separator"
                        },
                        "lblUsers": {
                            "@class": "com.viz.ide.model.segment.SimpleTextSegmentData",
                            "text": "Pay a Person from"
                        }
                    },
                    {
                        "lblSeparator": {
                            "@class": "com.viz.ide.model.segment.SimpleTextSegmentData",
                            "text": "Separator"
                        },
                        "lblUsers": {
                            "@class": "com.viz.ide.model.segment.SimpleTextSegmentData",
                            "text": "Order Check"
                        }
                    },
                    {
                        "lblSeparator": {
                            "@class": "com.viz.ide.model.segment.SimpleTextSegmentData",
                            "text": "Separator"
                        },
                        "lblUsers": {
                            "@class": "com.viz.ide.model.segment.SimpleTextSegmentData",
                            "text": "Edit Account"
                        }
                    },
                    {
                        "lblSeparator": {
                            "@class": "com.viz.ide.model.segment.SimpleTextSegmentData",
                            "text": "Separator"
                        },
                        "lblUsers": {
                            "@class": "com.viz.ide.model.segment.SimpleTextSegmentData",
                            "text": "Download Statement"
                        }
                    },
                    {
                        "lblSeparator": {
                            "@class": "com.viz.ide.model.segment.SimpleTextSegmentData",
                            "text": "Separator"
                        },
                        "lblUsers": {
                            "@class": "com.viz.ide.model.segment.SimpleTextSegmentData",
                            "text": "Settings & Alerts"
                        }
                    }
                ]
            },
            "height": {
                "Default": {
                    "type": "ref",
                    "value": "preferred"
                }
            },
            "maxHeight": {
                "Default": {
                    "type": "string",
                    "value": ""
                }
            },
            "width": {
                "Default": {
                    "type": "string",
                    "value": "100%"
                }
            }
        }
    },
    "id": "moreActionsDup",
    "info": null,
    "isdatareferenced": false,
    "isvisible": false,
    "kuid": "f4c7015efc5d4827bd5dd8a218249bfe",
    "layouttype": 4,
    "masterType": 0,
    "name": "kony.ui.UserWidgetInstance",
    "parent": "flxMainWrapper",
    "pf": "frmViewStatements",
    "snaptogrid": true,
    "sourceUserWidget": "b62c12eb1c8d4c288d0cc6b63f1eb6bb",
    "vizprops": {
        "hidewidgethierarchy": false
    },
    "wType": "UserWidgetInstance",
    "zindex": 10
}