{
  "android": {
    "font_name": "SourceSansPro-Semibold",
    "font_size": 125,
    "isForked": false
  },
  "androidwearos": {
    "font_size": 167,
    "isForked": false
  },
  "background_color": "00000000",
  "bg_type": "one",
  "border_color": "000d19ff",
  "border_style": "plain",
  "border_type": 0,
  "border_width": 0,
  "desktopweb": {
    "font_size": 284,
    "isForked": false
  },
  "fontSizeInPx": true,
  "font_color": "000d19ff",
  "font_name": "Helvetica",
  "font_size": 167,
  "font_style": "normal",
  "font_weight": "normal",
  "ipad": {
    "font_size": 167,
    "isForked": false
  },
  "iphone": {
    "font_name": "SourceSansPro-Semibold",
    "font_size": 167,
    "isForked": false
  },
  "isDefaultSkin": false,
  "kuid": "s7ca2856342c429382dcbeb86245807f",
  "tabrcandroid": {
    "font_size": 284,
    "isForked": false
  },
  "wType": "Label",
  "watchos": {
    "font_size": 167,
    "isForked": false
  }
}