{
    "@class": "com.kony.gen.viz.model.component.KVizLabel",
    "DNDConfig": null,
    "_height_": {
        "type": "string",
        "value": "100%"
    },
    "_left_": {
        "type": "string",
        "value": "4dp"
    },
    "_margin_": [
        1,
        1,
        1,
        1
    ],
    "_padding_": [
        0,
        0,
        0,
        0
    ],
    "_skin_": "s9d6ef635a6e4ea2b6b70467b8020751",
    "_text_": "",
    "_top_": {
        "type": "string",
        "value": "0"
    },
    "_width_": {
        "type": "ref",
        "value": "preferred"
    },
    "_wrapping_": 2,
    "accessibilityconfig": {
        "tagName": "span"
    },
    "android": {
        "textStyle": {
            "letterSpacing": 0,
            "strikeThrough": false
        }
    },
    "canUpdateUI": true,
    "centery": {
        "type": "number",
        "value": ""
    },
    "containerweight": 100,
    "contentalignment": 4,
    "id": "lblBack",
    "info": null,
    "ipad": {
        "psp": {
            "wrapping": 2
        }
    },
    "iphone": {
        "psp": {
            "wrapping": 2
        }
    },
    "iscustomlayout": false,
    "isvisible": true,
    "kuid": "jf3c2a7ac521430fa2c971498a1d2c66",
    "name": "kony.ui.Label",
    "parent": "flxImgBackNavigation",
    "pf": "frmSimulateEarlyPayOff",
    "responsiveData": {
        "b1": {
            "centerY": {
                "type": "string",
                "value": ""
            },
            "height": {
                "type": "string",
                "value": "100%"
            },
            "skin": "s9d6ef635a6e4ea2b6b70467b8020751",
            "top": {
                "type": "string",
                "value": ""
            }
        },
        "b2": {
            "centerY": {
                "type": "string",
                "value": "50%"
            },
            "skin": "s9d6ef635a6e4ea2b6b70467b8020751",
            "top": {
                "type": "string",
                "value": ""
            }
        },
        "b3": {
            "centerY": {
                "type": "string",
                "value": "50%"
            },
            "skin": "s9d6ef635a6e4ea2b6b70467b8020751",
            "top": {
                "type": "string",
                "value": ""
            }
        }
    },
    "retaincontentalignment": false,
    "retainflexpositionproperties": false,
    "texti18n": "i18n.CardManagement.Back",
    "tooltip": "",
    "wType": "Label"
}